Workbook

Sheet README
A1: Week 1 — Excel & Data Cleaning: Practice Questions + Course Project
A3: Data Analyst Course — Codec Technologies
A5: This workbook completes the Week 1 practice set and the course project.
A6: Dataset: a synthetic Global-Superstore-style sales dataset (180 cleaned rows, 3 years, 2023-2025),
A7: built to match the columns needed by every task below.
A9: PRACTICE QUESTIONS (practice_set.pdf):
A10: 1. Remove duplicates / handle missing values -> see "Raw_Data" and "Cleaned_Data" tabs
A11: 2. Pivot Table: region-wise sales -> "Analysis" tab, Task 2
A12: 3. Mean, median, mode via formulas -> "Analysis" tab, Task 3
A13: 4. Conditional formatting: top 10 sales -> "Cleaned_Data" tab, Sales column (red highlight)
A14: 5. Bar chart: category-wise revenue -> "Charts" tab
A16: COURSE PROJECT (week_1_1.pdf) — Pivot Table Dashboard:
... A28: Swap in the real file on the Raw_Data tab and every formula/chart will recompute.

Sheet Raw_Data
A1: RAW DATA (as exported) — contains duplicates and missing values
A3: Order ID | B3: Order Date | C3: Customer Name | D3: Region | E3: Category | F3: Sub-Category | G3: Product Name | H3: Department | I3: Quantity | J3: Sales | K3: Discount | L3: Profit | N3: Note:
A4: ORD-1166 | B4: 2025-04-11 | C4: Rohan Mehta | D4: East | E4: Technology | F4: Machines | G4: Machines Model 131 | H4: Corporate | I4: 6 | J4: 1890.96 | K4: 0.2 | L4: 383.98 | N4: This tab mirrors the raw export: 12 duplicate rows and blanks in Customer Name / Quantity / Sales were intentionally left in place so the cleaning steps on the Cleaned_Data tab are visible.
A5: ORD-1156 | B5: 2025-11-21 | C5: Aarav Sharma | D5: South | E5: Office Supplies | F5: Binders | G5: Binders Model 101 | H5: Consumer | I5: 10 | J5: 1565.3 | K5: 0 | L5: 215.04
A6: ORD-1064 | B6: 2024-10-22 | D6: South | E6: Technology | F6: Machines | G6: Machines Model 561 | H6: Corporate | I6: 4 | J6: 2003.92 | K6: 0 | L6: 267.88
A7: ORD-1136 | B7: 2025-07-08 | C7: Sanjay Reddy | D7: South | E7: Technology | F7: Phones | G7: Phones Model 739 | H7: Consumer | I7: 11 | J7: 6111.93 | K7: 0.15 | L7: 1261.89
A8: ORD-1176 | B8: 2024-04-06 | C8: Aditya Joshi | D8: West | E8: Furniture | F8: Bookcases | G8: Bookcases Model 966 | H8: Consumer | I8: 6 | J8: 3415.68 | K8: 0.15 | L8: 924.65
A9: ORD-1090 | B9: 2024-05-04 | C9: Karan Malhotra | D9: North | E9: Technology | F9: Machines | G9: Machines Model 144 | H9: Corporate | I9: 10 | J9: 2390.4 | K9: 0.3 | L9: 472.97
A10: ORD-1082 | B10: 2024-08-13 | C10: Pooja Desai | D10: South | E10: Furniture | F10: Tables | G10: Tables Model 137 | H10: Corporate | I10: 11 | J10: 6247.34 | K10: 0.3 | L10: 1216.39
A11: ORD-1067 | B11: 2023-02-05 | C11: Sanjay Reddy | D11: South | E11: Furniture | F11: Furnishings | G11: Furnishings Model 413 | H11: Home Office | I11: 2 | J11: 374.26 | K11: 0.1 | L11: 86.75
A12: ORD-1059 | B12: 2024-06-08 | C12: Sanjay Reddy | D12: West | E12: Office Supplies | F12: Binders | G12: Binders Model 835 | H12: Home Office | I12: 6 | J12: 678.96 | K12: 0.15 | L12: 195.71
A13: ORD-1062 | B13: 2023-05-22 | C13: Meera Pillai | D13: South | E13: Furniture | F13: Bookcases | G13: Bookcases Model 942 | H13: Home Office | I13: 9 | J13: 3544.29 | K13: 0 | L13: 1080.56
A14: ORD-1006 | B14: 2024-07-23 | D14: East | E14: Office Supplies | F14: Binders | G14: Binders Model 463 | H14: Consumer | I14: 8 | J14: 3095.04 | K14: 0 | L14: 305.78
A15: ORD-1002 | B15: 2024-03-23 | C15: Rohan Mehta | D15: East | E15: Furniture | F15: Furnishings | G15: Furnishings Model 833 | H15: Consumer | I15: 4 | J15: 1242.52 | K15: 0 | L15: 271.33
A16: ORD-1081 | B16: 2025-10-04 | C16: Divya Menon | D16: West | E16: Technology | F16: Machines | G16: Machines Model 786 | H16: Corporate | I16: 2 | J16: 579.92 | K16: 0.1 | L16: 78.29
A17: ORD-1046 | B17: 2024-02-12 | C17: Isha Kapoor | D17: North | E17: Office Supplies | F17: Binders | G17: Binders Model 725 | H17: Consumer | I17: 3 | J17: 87.87 | K17: 0 | L17: 30.33
A18: ORD-1001 | B18: 2024-04-02 | C18: Isha Kapoor | D18: North | E18: Technology | F18: Phones | G18: Phones Model 658 | H18: Consumer | I18: 3 | J18: 1337.52 | K18: 0.2 | L18: 291.26
A19: ORD-1058 | B19: 2024-05-21 | C19: Aarav Sharma | D19: East | E19: Furniture | F19: Chairs | G19: Chairs Model 229 | H19: Home Office | I19: 4 | J19: 2023.8 | K19: 0.15 | L19: 164.65
A20: ORD-1147 | B20: 2025-02-10 | C20: Vikram Rao | D20: North | E20: Technology | F20: Phones | G20: Phones Model 739 | H20: Home Office | I20: 3 | J20: 329.73 | K20: 0.3 | L20: 59.52
A21: ORD-1055 | B21: 2023-09-19 | C21: Sanjay Reddy | D21: West | E21: Technology | F21: Machines | G21: Machines Model 778 | H21: Home Office | I21: 10 | J21: 3274.6 | K21: 0.1 | L21: 670.67
A22: ORD-1113 | B22: 2024-05-28 | C22: Vikram Rao | D22: West | E22: Furniture | F22: Chairs | G22: Chairs Model 115 | H22: Corporate | I22: 3 | J22: 237.93 | K22: 0.3 | L22: 9.62
A23: ORD-1083 | B23: 2023-08-26 | C23: Aditya Joshi | D23: North | E23: Office Supplies | F23: Binders | G23: Binders Model 773 | H23: Corporate | I23: 7 | J23: 3646.79 | K23: 0.3 | L23: 884.36
A24: ORD-1029 | B24: 2024-03-12 | C24: Rohan Mehta | D24: East | E24: Furniture | F24: Chairs | G24: Chairs Model 350 | H24: Corporate | I24: 9 | J24: 1531.26 | K24: 0 | L24: 481.21
A25: ORD-1134 | B25: 2023-06-06 | C25: Ananya Gupta | D25: North | E25: Office Supplies | F25: Storage | G25: Storage Model 894 | H25: Consumer | I25: 9 | J25: 3468.96 | K25: 0.15 | L25: 598.53
A26: ORD-1052 | B26: 2024-11-08 | C26: Divya Menon | D26: South | E26: Furniture | F26: Tables | G26: Tables Model 530 | H26: Consumer | I26: 9 | J26: 2588.13 | K26: 0 | L26: 290
... A49: ORD-1045 | B49: 2023-12-14 | C49: Pooja Desai | D49: West | E49: Office Supplies | F49: Art | G49: Art Model 734 | H49: Corporate | I49: 11 | J49: 710.71 | K49: 0.15 | L49: 150.52
A50: ORD-1128 | B50: 2025-11-15 | C50: Karan Malhotra | D50: North | E50: Technology | F50: Machines | G50: Machines Model 794 | H50: Corporate | I50: 2 | K50: 0 | L50: 58.56
A51: ORD-1164 | B51: 2024-08-24 | C51: Ananya Gupta | D51: South | E51: Furniture | F51: Furnishings | G51: Furnishings Model 413 | H51: Consumer | I51: 6 | J51: 450.12 | K51: 0 | L51: 111.75
A52: ORD-1047 | B52: 2025-10-09 | C52: Rahul Bhat | D52: West | E52: Furniture | F52: Furnishings | G52: Furnishings Model 868 | H52: Corporate | I52: 7 | J52: 1104.11 | K52: 0.2 | L52: 226.37
A53: ORD-1180 | B53: 2023-05-03 | C53: Rohan Mehta | D53: South | E53: Furniture | F53: Furnishings | G53: Furnishings Model 448 | H53: Corporate | I53: 3 | J53: 816.51 | K53: 0.1 | L53: 139.13
A54: ORD-1023 | B54: 2024-04-29 | C54: Rohan Mehta | D54: East | E54: Technology | F54: Phones | G54: Phones Model 510 | H54: Consumer | I54: 3 | J54: 758.25 | K54: 0.1 | L54: 77.88
A55: ORD-1114 | B55: 2023-12-23 | C55: Aarav Sharma | D55: North | E55: Office Supplies | F55: Paper | G55: Paper Model 216 | H55: Home Office | I55: 5 | J55: 228.25 | K55: 0.2 | L55: 32.19
A56: ORD-1119 | B56: 2025-04-27 | C56: Isha Kapoor | D56: South | E56: Technology | F56: Accessories | G56: Accessories Model 197 | H56: Corporate | I56: 6 | J56: 2994.24 | K56: 0.1 | L56: 471.05
A57: ORD-1174 | B57: 2023-06-01 | C57: Divya Menon | D57: South | E57: Technology | F57: Machines | G57: Machines Model 577 | H57: Home Office | I57: 3 | J57: 1751.52 | K57: 0.2 | L57: 101.24
A58: ORD-1115 | B58: 2025-11-17 | C58: Meera Pillai | D58: South | E58: Technology | F58: Phones | G58: Phones Model 729 | H58: Corporate | I58: 10 | J58: 788 | K58: 0.15 | L58: 78.01
A59: ORD-1140 | B59: 2023-03-22 | C59: Ananya Gupta | D59: East | E59: Office Supplies | F59: Binders | G59: Binders Model 724 | H59: Corporate | I59: 4 | J59: 1715.84 | K59: 0.1 | L59: 320
A60: ORD-1088 | B60: 2024-07-19 | C60: Rohan Mehta | D60: West | E60: Office Supplies | F60: Paper | G60: Paper Model 940 | H60: Home Office | I60: 7 | J60: 1496.81 | K60: 0.3 | L60: 211.99
A61: ORD-1097 | B61: 2025-10-16 | C61: Isha Kapoor | D61: South | E61: Furniture | F61: Tables | G61: Tables Model 570 | H61: Consumer | I61: 10 | J61: 987.2 | K61: 0.1 | L61: 214.45
A62: ORD-1125 | B62: 2023-10-18 | C62: Rohan Mehta | D62: South | E62: Furniture | F62: Tables | G62: Tables Model 643 | H62: Consumer | I62: 12 | J62: 4624.92 | K62: 0 | L62: 358.56
... A70: ORD-1132 | B70: 2024-08-15 | C70: Divya Menon | D70: South | E70: Office Supplies | F70: Labels | G70: Labels Model 732 | H70: Corporate | I70: 2 | J70: 503.88 | K70: 0 | L70: 51.18
A71: ORD-1120 | B71: 2023-11-09 | D71: North | E71: Office Supplies | F71: Art | G71: Art Model 187 | H71: Corporate | J71: 6104.45 | K71: 0 | L71: 472.29
A72: ORD-1071 | B72: 2025-10-02 | C72: Vikram Rao | D72: North | E72: Office Supplies | F72: Binders | G72: Binders Model 590 | H72: Consumer | I72: 2 | J72: 1051.08 | K72: 0.15 | L72: 120.88
A73: ORD-1027 | B73: 2023-03-23 | C73: Isha Kapoor | D73: East | E73: Technology | F73: Accessories | G73: Accessories Model 635 | H73: Corporate | I73: 10 | J73: 629.6 | K73: 0.2 | L73: 113.38
A74: ORD-1053 | B74: 2025-09-03 | C74: Rahul Bhat | D74: East | E74: Office Supplies | F74: Labels | G74: Labels Model 973 | H74: Home Office | I74: 1 | J74: 566.5 | K74: 0 | L74: 156.38
A75: ORD-1020 | B75: 2024-01-25 | C75: Divya Menon | D75: South | E75: Technology | F75: Machines | G75: Machines Model 520 | H75: Consumer | I75: 2 | J75: 143.4 | K75: 0.1 | L75: 20.17
A76: ORD-1175 | B76: 2025-06-05 | C76: Vikram Rao | D76: West | E76: Technology | F76: Copiers | G76: Copiers Model 630 | H76: Consumer | I76: 9 | J76: 4929.93 | K76: 0 | L76: 1476.11
A77: ORD-1041 | B77: 2025-11-30 | C77: Aarav Sharma | D77: South | E77: Furniture | F77: Bookcases | G77: Bookcases Model 301 | H77: Consumer | I77: 9 | J77: 3751.29 | K77: 0.2 | L77: 813.61
A78: ORD-1057 | B78: 2024-05-31 | C78: Divya Menon | D78: North | E78: Office Supplies | F78: Storage | G78: Storage Model 458 | H78: Corporate | I78: 2 | J78: 580.26 | K78: 0.2 | L78: 98.33
A79: ORD-1110 | B79: 2023-07-23 | C79: Meera Pillai | D79: West | E79: Furniture | F79: Furnishings | G79: Furnishings Model 507 | H79: Corporate | I79: 11 | J79: 2528.79 | K79: 0.2 | L79: 318.83
A80: ORD-1152 | B80: 2025-04-29 | C80: Aarav Sharma | D80: North | E80: Furniture | F80: Tables | G80: Tables Model 183 | H80: Corporate | I80: 1 | J80: 246.93 | K80: 0 | L80: 29.81
A81: ORD-1106 | B81: 2023-08-10 | C81: Meera Pillai | D81: South | E81: Technology | F81: Copiers | G81: Copiers Model 674 | H81: Home Office | I81: 11 | J81: 1669.69 | K81: 0 | L81: 393.82
A82: ORD-1092 | B82: 2023-02-01 | C82: Sanjay Reddy | D82: East | E82: Office Supplies | F82: Binders | G82: Binders Model 258 | H82: Corporate | I82: 12 | J82: 1191.96 | K82: 0.3 | L82: 205.62
A83: ORD-1005 | B83: 2025-01-10 | C83: Neha Verma | D83: East | E83: Technology | F83: Phones | G83: Phones Model 333 | H83: Corporate | I83: 10 | J83: 1274.9 | K83: 0 | L83: 81.27
... A85: ORD-1160 | B85: 2023-10-04 | C85: Ananya Gupta | D85: South | E85: Technology | F85: Machines | G85: Machines Model 306 | H85: Home Office | I85: 2 | J85: 867.78 | K85: 0.1 | L85: 47.72
A86: ORD-1049 | B86: 2025-10-30 | D86: North | E86: Office Supplies | F86: Labels | G86: Labels Model 262 | H86: Home Office | I86: 7 | J86: 3506.16 | K86: 0.15 | L86: 547.69
A87: ORD-1080 | B87: 2024-07-05 | C87: Aarav Sharma | D87: West | E87: Office Supplies | F87: Binders | G87: Binders Model 631 | H87: Consumer | I87: 10 | J87: 385.4 | K87: 0.3 | L87: 27.67
A88: ORD-1159 | B88: 2023-10-01 | C88: Aditya Joshi | D88: East | E88: Office Supplies | F88: Paper | G88: Paper Model 279 | H88: Home Office | I88: 1 | J88: 221.09 | K88: 0 | L88: 65.01
A89: ORD-1156 | B89: 2025-11-21 | C89: Aarav Sharma | D89: South | E89: Office Supplies | F89: Binders | G89: Binders Model 101 | H89: Consumer | I89: 10 | J89: 1565.3 | K89: 0 | L89: 215.04
A90: ORD-1022 | B90: 2024-07-24 | C90: Ananya Gupta | D90: South | E90: Furniture | F90: Furnishings | G90: Furnishings Model 982 | H90: Consumer | I90: 8 | J90: 1289.12 | K90: 0 | L90: 235.83
A91: ORD-1028 | B91: 2024-06-27 | C91: Isha Kapoor | D91: North | E91: Office Supplies | F91: Storage | G91: Storage Model 423 | H91: Consumer | I91: 7 | J91: 640.92 | K91: 0.2 | L91: 71.78
A92: ORD-1151 | B92: 2023-06-21 | C92: Neha Verma | D92: East | E92: Office Supplies | F92: Labels | G92: Labels Model 547 | H92: Consumer | I92: 3 | J92: 523.74 | K92: 0.15 | L92: 41.94
A93: ORD-1007 | B93: 2025-12-29 | C93: Ananya Gupta | D93: East | E93: Furniture | F93: Bookcases | G93: Bookcases Model 755 | H93: Home Office | I93: 12 | J93: 1898.52 | K93: 0.1 | L93: 279.94
A94: ORD-1030 | B94: 2025-12-19 | C94: Neha Verma | D94: South | E94: Office Supplies | F94: Storage | G94: Storage Model 779 | H94: Consumer | I94: 1 | J94: 405.7 | K94: 0.15 | L94: 48.21
A95: ORD-1161 | B95: 2025-11-21 | C95: Neha Verma | D95: North | E95: Furniture | F95: Tables | G95: Tables Model 137 | H95: Consumer | I95: 7 | J95: 4155.48 | K95: 0.15 | L95: 678.24
A96: ORD-1171 | B96: 2024-10-16 | C96: Rohan Mehta | D96: South | E96: Furniture | F96: Furnishings | G96: Furnishings Model 397 | H96: Consumer | I96: 11 | J96: 2400.64 | K96: 0 | L96: 516.14
A97: ORD-1158 | B97: 2025-03-03 | C97: Priya Nair | D97: South | E97: Technology | F97: Phones | G97: Phones Model 169 | H97: Corporate | J97: 980.34 | K97: 0 | L97: 154.04
A98: ORD-1034 | B98: 2023-10-31 | C98: Meera Pillai | D98: East | E98: Technology | F98: Accessories | G98: Accessories Model 915 | H98: Home Office | I98: 7 | J98: 626.92 | K98: 0 | L98: 99.93
A99: ORD-1112 | B99: 2024-02-29 | C99: Rohan Mehta | D99: West | E99: Furniture | F99: Tables | G99: Tables Model 892 | H99: Home Office | I99: 10 | J99: 1413.3 | K99: 0.3 | L99: 118.62
A100: ORD-1077 | B100: 2023-08-24 | C100: Divya Menon | D100: West | E100: Furniture | F100: Tables | G100: Tables Model 946 | H100: Corporate | I100: 9 | J100: 1318.59 | K100: 0 | L100: 425.28
A101: ORD-1004 | B101: 2025-01-05 | C101: Sneha Iyer | D101: South | E101: Office Supplies | F101: Binders | G101: Binders Model 570 | H101: Consumer | I101: 6 | J101: 2209.08 | K101: 0.3 | L101: 97.47
A102: ORD-1081 | B102: 2025-10-04 | C102: Divya Menon | D102: West | E102: Technology | F102: Machines | G102: Machines Model 786 | H102: Corporate | I102: 2 | J102: 579.92 | K102: 0.1 | L102: 78.29
A103: ORD-1089 | B103: 2023-11-01 | C103: Pooja Desai | D103: North | E103: Furniture | F103: Bookcases | G103: Bookcases Model 881 | H103: Home Office | J103: 2640.56 | K103: 0 | L103: 395.38
A104: ORD-1163 | B104: 2025-10-13 | C104: Ananya Gupta | D104: North | E104: Technology | F104: Machines | G104: Machines Model 920 | H104: Corporate | I104: 12 | J104: 3672.6 | K104: 0.3 | L104: 529.03
A105: ORD-1102 | B105: 2024-09-24 | C105: Priya Nair | D105: East | E105: Technology | F105: Accessories | G105: Accessories Model 192 | H105: Home Office | I105: 8 | J105: 276.16 | K105: 0 | L105: 74.48
A106: ORD-1040 | B106: 2024-10-04 | C106: Meera Pillai | D106: South | E106: Furniture | F106: Chairs | G106: Chairs Model 690 | H106: Home Office | I106: 7 | J106: 2587.41 | K106: 0.15 | L106: 186.27
A107: ORD-1075 | B107: 2023-06-16 | C107: Arjun Singh | D107: West | E107: Furniture | F107: Chairs | G107: Chairs Model 102 | H107: Consumer | J107: 465.96 | K107: 0.15 | L107: 28.72
A108: ORD-1054 | B108: 2024-03-25 | C108: Pooja Desai | D108: West | E108: Office Supplies | F108: Labels | G108: Labels Model 784 | H108: Home Office | I108: 5 | J108: 1349.8 | K108: 0 | L108: 224.95
A109: ORD-1015 | B109: 2025-09-22 | C109: Rohan Mehta | D109: East | E109: Furniture | F109: Tables | G109: Tables Model 231 | H109: Home Office | I109: 2 | J109: 1174.24 | K109: 0.15 | L109: 279.22
A110: ORD-1149 | B110: 2025-01-23 | C110: Karan Malhotra | D110: South | E110: Furniture | F110: Tables | G110: Tables Model 388 | H110: Corporate | I110: 11 | J110: 6259.77 | K110: 0.1 | L110: 1061.99
A111: ORD-1043 | B111: 2024-01-28 | C111: Vikram Rao | D111: North | E111: Office Supplies | F111: Art | G111: Art Model 278 | H111: Home Office | I111: 7 | J111: 2827.86 | K111: 0.1 | L111: 644.4
A112: ORD-1048 | B112: 2023-04-13 | C112: Sanjay Reddy | D112: West | E112: Furniture | F112: Furnishings | G112: Furnishings Model 236 | H112: Consumer | I112: 9 | J112: 1447.02 | K112: 0.3 | L112: 87.52
A113: ORD-1177 | B113: 2024-09-12 | C113: Vikram Rao | D113: North | E113: Furniture | F113: Bookcases | G113: Bookcases Model 706 | H113: Consumer | I113: 10 | J113: 3270.8 | K113: 0.15 | L113: 673.63
A114: ORD-1105 | B114: 2025-03-19 | C114: Rohan Mehta | D114: North | E114: Technology | F114: Machines | G114: Machines Model 788 | H114: Home Office | I114: 1 | J114: 169.71 | K114: 0 | L114: 31.64
A115: ORD-1061 | B115: 2024-09-09 | C115: Sneha Iyer | D115: West | E115: Furniture | F115: Chairs | G115: Chairs Model 679 | H115: Home Office | I115: 11 | J115: 4028.64 | K115: 0 | L115: 1163.75
A116: ORD-1123 | B116: 2025-01-22 | C116: Meera Pillai | D116: East | E116: Furniture | F116: Furnishings | G116: Furnishings Model 539 | H116: Consumer | I116: 2 | J116: 922.24 | K116: 0.15 | L116: 92.38
A117: ORD-1089 | B117: 2023-11-01 | C117: Pooja Desai | D117: North | E117: Furniture | F117: Bookcases | G117: Bookcases Model 881 | H117: Home Office | J117: 2640.56 | K117: 0 | L117: 395.38
A118: ORD-1095 | B118: 2023-12-07 | C118: Sanjay Reddy | D118: East | E118: Furniture | F118: Furnishings | G118: Furnishings Model 915 | H118: Consumer | I118: 12 | J118: 2282.28 | K118: 0 | L118: 145.6
A119: ORD-1063 | B119: 2023-11-10 | C119: Sanjay Reddy | D119: North | E119: Office Supplies | F119: Binders | G119: Binders Model 376 | H119: Corporate | I119: 7 | J119: 826.28 | K119: 0.15 | L119: 238.54
A120: ORD-1069 | B120: 2024-01-28 | C120: Ananya Gupta | D120: East | E120: Furniture | F120: Tables | G120: Tables Model 878 | H120: Corporate | J120: 1788.32 | K120: 0 | L120: 478.15
A121: ORD-1066 | B121: 2025-11-24 | C121: Aarav Sharma | D121: North | E121: Office Supplies | F121: Storage | G121: Storage Model 668 | H121: Corporate | I121: 4 | J121: 260.32 | K121: 0.2 | L121: 35.81
A122: ORD-1107 | B122: 2024-09-10 | C122: Sanjay Reddy | D122: East | E122: Office Supplies | F122: Labels | G122: Labels Model 138 | H122: Consumer | I122: 11 | J122: 2792.35 | K122: 0 | L122: 177.6
A123: ORD-1065 | B123: 2023-02-28 | C123: Aditya Joshi | D123: South | E123: Furniture | F123: Furnishings | G123: Furnishings Model 463 | H123: Home Office | I123: 8 | J123: 4102.48 | K123: 0 | L123: 805.17
A124: ORD-1044 | B124: 2024-08-10 | C124: Neha Verma | D124: East | E124: Technology | F124: Copiers | G124: Copiers Model 429 | H124: Corporate | I124: 4 | J124: 1065.92 | K124: 0.15 | L124: 210.2
A125: ORD-1076 | B125: 2023-03-08 | C125: Neha Verma | D125: South | E125: Office Supplies | F125: Art | G125: Art Model 564 | H125: Home Office | I125: 4 | J125: 734.16 | K125: 0 | L125: 191.54
A126: ORD-1135 | B126: 2023-07-30 | C126: Isha Kapoor | D126: West | E126: Office Supplies | F126: Storage | G126: Storage Model 878 | H126: Home Office | I126: 3 | J126: 494.22 | K126: 0 | L126: 114.03
A127: ORD-1108 | B127: 2023-10-05 | C127: Isha Kapoor | D127: East | E127: Office Supplies | F127: Art | G127: Art Model 813 | H127: Consumer | I127: 7 | J127: 1962.66 | K127: 0.2 | L127: 525.7
A128: ORD-1095 | B128: 2023-12-07 | C128: Sanjay Reddy | D128: East | E128: Furniture | F128: Furnishings | G128: Furnishings Model 915 | H128: Consumer | I128: 12 | J128: 2282.28 | K128: 0 | L128: 145.6
A129: ORD-1079 | B129: 2023-06-14 | C129: Sanjay Reddy | D129: South | E129: Office Supplies | F129: Labels | G129: Labels Model 718 | H129: Home Office | J129: 383.2 | K129: 0.1 | L129: 93.24
A130: ORD-1145 | B130: 2025-01-12 | C130: Aarav Sharma | D130: North | E130: Furniture | F130: Furnishings | G130: Furnishings Model 884 | H130: Home Office | I130: 5 | J130: 602.25 | K130: 0 | L130: 91.85
A131: ORD-1042 | B131: 2023-09-13 | C131: Aditya Joshi | D131: North | E131: Office Supplies | F131: Art | G131: Art Model 518 | H131: Consumer | I131: 12 | J131: 6498.36 | K131: 0.15 | L131: 788.69
...

Sheet Cleaned_Data
A1: CLEANED DATA — Task 1: duplicates removed, missing values handled
A2: Task 4: conditional formatting highlights the TOP 10 highest values in the Sales column (red fill).
A3: Order ID | B3: Order Date | C3: Customer Name | D3: Region | E3: Category | F3: Sub-Category | G3: Product Name | H3: Department | I3: Quantity | J3: Sales | K3: Discount | L3: Profit | M3: Year | O3: Cleaning steps applied
A4: ORD-1001 | B4: 2024-04-02 | C4: Isha Kapoor | D4: North | E4: Technology | F4: Phones | G4: Phones Model 658 | H4: Consumer | I4: 3 | J4: 1337.52 | K4: 0.2 | L4: 291.26 | M4: 2024 | O4: 1. Removed 12 exact duplicate rows (drop_duplicates).
A5: ORD-1002 | B5: 2024-03-23 | C5: Rohan Mehta | D5: East | E5: Furniture | F5: Furnishings | G5: Furnishings Model 833 | H5: Consumer | I5: 4 | J5: 1242.52 | K5: 0 | L5: 271.33 | M5: 2024 | O5: 2. Blank "Customer Name" -> filled with "Unknown Customer".
A6: ORD-1003 | B6: 2023-01-14 | C6: Arjun Singh | D6: South | E6: Technology | F6: Machines | G6: Machines Model 320 | H6: Consumer | I6: 3 | J6: 1270.23 | K6: 0 | L6: 169.4 | M6: 2023 | O6: 3. Blank "Quantity" -> filled with the column median.
A7: ORD-1004 | B7: 2025-01-05 | C7: Sneha Iyer | D7: South | E7: Office Supplies | F7: Binders | G7: Binders Model 570 | H7: Consumer | I7: 6 | J7: 2209.08 | K7: 0.3 | L7: 97.47 | M7: 2025 | O7: 4. Blank "Sales" -> filled with the column median.
A8: ORD-1005 | B8: 2025-01-10 | C8: Neha Verma | D8: East | E8: Technology | F8: Phones | G8: Phones Model 333 | H8: Corporate | I8: 10 | J8: 1274.9 | K8: 0 | L8: 81.27 | M8: 2025 | O8: Result: 192 raw rows -> 180 cleaned rows.
A9: ORD-1006 | B9: 2024-07-23 | C9: Unknown Customer | D9: East | E9: Office Supplies | F9: Binders | G9: Binders Model 463 | H9: Consumer | I9: 8 | J9: 3095.04 | K9: 0 | L9: 305.78 | M9: 2024
A10: ORD-1007 | B10: 2025-12-29 | C10: Ananya Gupta | D10: East | E10: Furniture | F10: Bookcases | G10: Bookcases Model 755 | H10: Home Office | I10: 12 | J10: 1898.52 | K10: 0.1 | L10: 279.94 | M10: 2025
A11: ORD-1008 | B11: 2024-04-14 | C11: Priya Nair | D11: North | E11: Technology | F11: Accessories | G11: Accessories Model 316 | H11: Home Office | I11: 1 | J11: 485.95 | K11: 0.1 | L11: 57 | M11: 2024
A12: ORD-1009 | B12: 2025-07-28 | C12: Rahul Bhat | D12: South | E12: Technology | F12: Copiers | G12: Copiers Model 651 | H12: Consumer | I12: 3 | J12: 509.85 | K12: 0 | L12: 139.44 | M12: 2025
A13: ORD-1010 | B13: 2024-03-25 | C13: Meera Pillai | D13: South | E13: Office Supplies | F13: Labels | G13: Labels Model 981 | H13: Corporate | I13: 3 | J13: 939.21 | K13: 0 | L13: 259.91 | M13: 2024
A14: ORD-1011 | B14: 2023-05-11 | C14: Divya Menon | D14: West | E14: Furniture | F14: Tables | G14: Tables Model 666 | H14: Home Office | I14: 7 | J14: 1667.75 | K14: 0.1 | L14: 313.3 | M14: 2023
A15: ORD-1012 | B15: 2023-08-17 | C15: Aditya Joshi | D15: North | E15: Furniture | F15: Chairs | G15: Chairs Model 839 | H15: Home Office | I15: 5 | J15: 1346.7 | K15: 0.1 | L15: 61.78 | M15: 2023
A16: ORD-1013 | B16: 2024-09-03 | C16: Sneha Iyer | D16: West | E16: Technology | F16: Copiers | G16: Copiers Model 880 | H16: Home Office | I16: 11 | J16: 3431.78 | K16: 0 | L16: 328.94 | M16: 2024
A17: ORD-1014 | B17: 2023-02-09 | C17: Pooja Desai | D17: North | E17: Furniture | F17: Chairs | G17: Chairs Model 345 | H17: Home Office | I17: 2 | J17: 1117.04 | K17: 0.3 | L17: 228.35 | M17: 2023
A18: ORD-1015 | B18: 2025-09-22 | C18: Rohan Mehta | D18: East | E18: Furniture | F18: Tables | G18: Tables Model 231 | H18: Home Office | I18: 2 | J18: 1174.24 | K18: 0.15 | L18: 279.22 | M18: 2025
A19: ORD-1016 | B19: 2025-12-16 | C19: Arjun Singh | D19: West | E19: Technology | F19: Machines | G19: Machines Model 873 | H19: Home Office | I19: 10 | J19: 2625.4 | K19: 0 | L19: 862.9 | M19: 2025
A20: ORD-1017 | B20: 2025-02-03 | C20: Rahul Bhat | D20: North | E20: Technology | F20: Accessories | G20: Accessories Model 330 | H20: Home Office | I20: 8 | J20: 4330.16 | K20: 0.1 | L20: 336.33 | M20: 2025
... A183: ORD-1180 | B183: 2023-05-03 | C183: Rohan Mehta | D183: South | E183: Furniture | F183: Furnishings | G183: Furnishings Model 448 | H183: Corporate | I183: 3 | J183: 816.51 | K183: 0.1 | L183: 139.13 | M183: 2023

Sheet Analysis
A1: ANALYSIS — Pivot-style Summaries & Descriptive Statistics
A3: Task 2: Pivot Table — Region-wise Sales
A4: Region | B4: Total Sales
A5: East | B5: =SUMIF(Cleaned_Data!$D$4:$D$183,A5,Cleaned_Data!$J$4:$J$183) -> 56137.42
A6: West | B6: =SUMIF(Cleaned_Data!$D$4:$D$183,A6,Cleaned_Data!$J$4:$J$183) -> 70673.32
A7: North | B7: =SUMIF(Cleaned_Data!$D$4:$D$183,A7,Cleaned_Data!$J$4:$J$183) -> 110459.44
A8: South | B8: =SUMIF(Cleaned_Data!$D$4:$D$183,A8,Cleaned_Data!$J$4:$J$183) -> 124852.41
A9: Grand Total | B9: =SUM(B5:B8) -> 362122.59
A11: Task 3: Descriptive Statistics (Excel formulas)
A12: Metric | B12: Sales | C12: Quantity
A13: Mean | B13: =AVERAGE(Cleaned_Data!$J$4:$J$183) -> 2011.7922 | C13: =AVERAGE(Cleaned_Data!$I$4:$I$183) -> 6.6
A14: Median | B14: =MEDIAN(Cleaned_Data!$J$4:$J$183) -> 1454.96 | C14: =MEDIAN(Cleaned_Data!$I$4:$I$183) -> 7
A15: Mode | B15: =MODE(Cleaned_Data!$J$4:$J$183) -> 1454.96 | C15: =MODE(Cleaned_Data!$I$4:$I$183) -> 7
A18: Task 5: Category-wise Revenue (source data for bar chart)
A19: Category | B19: Revenue
A20: Furniture | B20: =SUMIF(Cleaned_Data!$E$4:$E$183,A20,Cleaned_Data!$J$4:$J$183) -> 150849.74
A21: Office Supplies | B21: =SUMIF(Cleaned_Data!$E$4:$E$183,A21,Cleaned_Data!$J$4:$J$183) -> 109018.16
A22: Technology | B22: =SUMIF(Cleaned_Data!$E$4:$E$183,A22,Cleaned_Data!$J$4:$J$183) -> 102254.69
A24: Project: Total Revenue
A25: Total Revenue | B25: =SUM(Cleaned_Data!$J$4:$J$183) -> 362122.59
A26: Total Profit | B26: =SUM(Cleaned_Data!$L$4:$L$183) -> 63640.54
A27: Total Orders | B27: =COUNTA(Cleaned_Data!$J$4:$J$183) -> 180
A29: Project: Yearly Sales Trends
A30: Year | B30: Total Sales
A31: 2023 | B31: =SUMIF(Cleaned_Data!$M$4:$M$183,A31,Cleaned_Data!$J$4:$J$183) -> 129909.33
A32: 2024 | B32: =SUMIF(Cleaned_Data!$M$4:$M$183,A32,Cleaned_Data!$J$4:$J$183) -> 126611.87
A33: 2025 | B33: =SUMIF(Cleaned_Data!$M$4:$M$183,A33,Cleaned_Data!$J$4:$J$183) -> 105601.39
A35: Project: Department-wise Revenue
A36: Department | B36: Revenue
A37: Consumer | B37: =SUMIF(Cleaned_Data!$H$4:$H$183,A37,Cleaned_Data!$J$4:$J$183) -> 125133.22
A38: Corporate | B38: =SUMIF(Cleaned_Data!$H$4:$H$183,A38,Cleaned_Data!$J$4:$J$183) -> 122763.72
A39: Home Office | B39: =SUMIF(Cleaned_Data!$H$4:$H$183,A39,Cleaned_Data!$J$4:$J$183) -> 114225.65

Sheet Charts
A1: CHARTS — Task 5 (Category Revenue) + Project Visuals
